accssctrl/__init__.py
accssctrl/accssctrl.py
accssctrl-0.1.0.dist-info/AUTHORS.rst
accssctrl-0.1.0.dist-info/LICENSE
accssctrl-0.1.0.dist-info/METADATA
accssctrl-0.1.0.dist-info/WHEEL
accssctrl-0.1.0.dist-info/top_level.txt
accssctrl-0.1.0.dist-info/RECORD
