Metadata-Version: 2.1
Name: accssctrl
Version: 0.1.0
Summary: Python Attribute Access Control
Home-page: https://github.com/sglumac/accssctrl
Author: Slaven Glumac
Author-email: slaven.glumac@gmail.com
License: BSD license
Keywords: accssctrl
Platform: UNKNOWN
Classifier: Development Status :: 2 - Pre-Alpha
Classifier: Intended Audience :: Developers
Classifier: License :: OSI Approved :: BSD License
Classifier: Natural Language :: English
Classifier: Programming Language :: Python :: 3
Classifier: Programming Language :: Python :: 3.6
Classifier: Programming Language :: Python :: 3.7
Classifier: Programming Language :: Python :: 3.8
Requires-Python: >=3.6
License-File: LICENSE
License-File: AUTHORS.rst
